dbtvault_generator/__init__.py
dbtvault_generator/app/Home.py
dbtvault_generator/cli/__init__.py
dbtvault_generator/cli/commands.py
dbtvault_generator/constants/__init__.py
dbtvault_generator/constants/exceptions.py
dbtvault_generator/constants/literals.py
dbtvault_generator/constants/types.py
dbtvault_generator/files/__init__.py
dbtvault_generator/files/file_io.py
dbtvault_generator/files/search.py
dbtvault_generator/generator/__init__.py
dbtvault_generator/generator/readers.py
dbtvault_generator/generator/runners.py
dbtvault_generator/generator/subprocess.py
dbtvault_generator/main.py
dbtvault_generator/parsers/__init__.py
dbtvault_generator/parsers/fmt_string.py
dbtvault_generator/parsers/params.py
dbtvault_generator/parsers/relationships.py
dbtvault_generator/parsers/templaters.py
src/dbtvault_generator/__version__.py
dbtvault_generator-0.2.3.dist-info/entry_points.txt
dbtvault_generator-0.2.3.dist-info/WHEEL
dbtvault_generator-0.2.3.dist-info/METADATA
dbtvault_generator-0.2.3.dist-info/licenses/LICENSE
dbtvault_generator-0.2.3.dist-info/RECORD
