Metadata-Version: 2.1
Name: dbtvault-generator
Version: 0.2.3
Summary: A little util to help you generate DBTVault SQL files from metadata, while we wait for DBTLabs to add meta to the execution context
License: Apache-2.0
Author-email: Alex Stenlake <alex.stenlake@gmail.com>
Requires-Python: >=3.9
Requires-Dist: dbt-artifacts-parser>=0.2.4
Requires-Dist: pydantic>=1.10.5
Requires-Dist: schema>=0.7.5
Requires-Dist: typer[all]>=0.7.0
